symbolx/__init__.py
symbolx/handler.py
symbolx/settings.py
symbolx/symbols.py
symbolx/utils.py
symbolx/parsers/__init__.py
symbolx/parsers/parser_csv.py
symbolx/parsers/parser_feather.py
symbolx/parsers/parser_gdx.py
symbolx-0.4.3.dist-info/LICENSE
symbolx-0.4.3.dist-info/METADATA
symbolx-0.4.3.dist-info/WHEEL
symbolx-0.4.3.dist-info/top_level.txt
symbolx-0.4.3.dist-info/RECORD
